YouTubeMusic/Models.py
YouTubeMusic/Playlist.py
YouTubeMusic/Search.py
YouTubeMusic/Startup.py
YouTubeMusic/Stream.py
YouTubeMusic/Update.py
YouTubeMusic/Utils.py
YouTubeMusic/YtSearch.py
YouTubeMusic/__init__.py
YouTubeMusic/cli.py
youtubemusic-2026.2.1.dist-info/licenses/LICENSE
youtubemusic-2026.2.1.dist-info/METADATA
youtubemusic-2026.2.1.dist-info/WHEEL
youtubemusic-2026.2.1.dist-info/entry_points.txt
youtubemusic-2026.2.1.dist-info/top_level.txt
youtubemusic-2026.2.1.dist-info/RECORD
