Metadata-Version: 2.4
Name: YouTubeMusic
Version: 2026.2.1
Summary: A YouTube Music Search Package With Artist, Channel, and Video Details
Home-page: https://github.com/YouTubeMusicAPI/YouTubeMusic
Author: ABHISHEK THAKUR
Author-email: ABHISHEK THAKUR <abhishekbanshiwal2005@gmail.com>
Requires-Python: >=3.8
License-File: LICENSE
Requires-Dist: httpx[http2]
Requires-Dist: orjson>=3.9.0
Requires-Dist: yt-dlp
Requires-Dist: redis[async]
Dynamic: author
Dynamic: home-page
Dynamic: license-file
Dynamic: requires-python
